[
  {
    "name": "AKBAR RISQ",
    "stock": 183,
    "lastStock": 0,
    "lastUpdate": "2026-04-24T05:10:43Z",
    "cycle": 1
  },
  {
    "name": "ATHI HANDAYANI",
    "stock": 16,
    "lastStock": 0,
    "lastUpdate": "2026-04-24T05:10:43Z",
    "cycle": 3
  },
  {
    "name": "CINDRAWATI",
    "stock": 55,
    "lastStock": 0,
    "lastUpdate": "2026-04-24T05:10:43Z",
    "cycle": 3
  },
  {
    "name": "EDI SUGENG SARIPAN",
    "stock": 26,
    "lastStock": 0,
    "lastUpdate": "2026-04-24T05:10:43Z",
    "cycle": 3
  },
  {
    "name": "BINA MAKMUR",
    "stock": 199,
    "lastStock": 0,
    "lastUpdate": "2026-04-24T05:14:02Z",
    "cycle": 1
  },
  {
    "name": "HENDRA KURNIAWAN",
    "stock": 121,
    "lastStock": 27,
    "lastUpdate": "2026-04-24T05:14:24Z",
    "cycle": 3
  },
  {
    "name": "SUCIYONO",
    "stock": 216,
    "lastStock": 0,
    "lastUpdate": "2026-04-24T05:15:15Z",
    "cycle": 1
  },
  {
    "name": "JAENAL",
    "stock": 218,
    "lastStock": 13,
    "lastUpdate": "2026-04-24T05:15:37Z",
    "cycle": 1
  },
  {
    "name": "JOKO SUWARNO",
    "stock": 140,
    "lastStock": 0,
    "lastUpdate": "2026-04-24T05:18:12Z",
    "cycle": 3
  },
  {
    "name": "KARSONO",
    "stock": 1,
    "lastStock": 0,
    "lastUpdate": "2026-04-23T17:18:40Z",
    "cycle": 0
  },
  {
    "name": "LUTFI A.",
    "stock": 130,
    "lastStock": 0,
    "lastUpdate": "2026-04-23T17:44:31Z",
    "cycle": 0
  },
  {
    "name": "MOH SAID",
    "stock": 40,
    "lastStock": 0,
    "lastUpdate": "2026-04-23T17:44:31Z",
    "cycle": 0
  },
  {
    "name": "TOKO 2 PUTRI",
    "stock": 38,
    "lastStock": 0,
    "lastUpdate": "2026-04-23T17:50:39Z",
    "cycle": 0
  },
  {
    "name": "TOKO IIN",
    "stock": 141,
    "lastStock": 0,
    "lastUpdate": "2026-04-23T17:50:39Z",
    "cycle": 0
  },
  {
    "name": "HJ LILIK LAILIYAH",
    "stock": 0,
    "lastStock": 0,
    "lastUpdate": "2026-04-24T02:22:56Z",
    "cycle": 0
  },
  {
    "name": "ERNA PUJIATI",
    "stock": 0,
    "lastStock": 0,
    "lastUpdate": "2026-04-24T02:22:56Z",
    "cycle": 0
  },
  {
    "name": "JONI H",
    "stock": 0,
    "lastStock": 0,
    "lastUpdate": "2026-04-24T02:27:22Z",
    "cycle": 0
  },
  {
    "name": "ROSA V",
    "stock": 0,
    "lastStock": 0,
    "lastUpdate": "2026-04-24T02:31:13Z",
    "cycle": 0
  },
  {
    "name": "LUKMAN BS",
    "stock": 0,
    "lastStock": 0,
    "lastUpdate": "2026-04-24T02:31:13Z",
    "cycle": 0
  },
  {
    "name": "BISTON MANURUNG",
    "stock": 0,
    "lastStock": 0,
    "lastUpdate": "2026-04-24T02:31:13Z",
    "cycle": 0
  },
  {
    "name": "JAMILAH",
    "stock": 0,
    "lastStock": 25,
    "lastUpdate": "2026-04-24T02:42:58Z",
    "cycle": 0
  },
  {
    "name": "YUDA",
    "stock": 15,
    "lastStock": 0,
    "lastUpdate": "2026-04-23T23:48:13Z",
    "cycle": 0
  },
  {
    "name": "BAMBANG HARTONO",
    "stock": 0,
    "lastStock": 0,
    "lastUpdate": "2026-04-24T02:42:58Z",
    "cycle": 0
  },
  {
    "name": "NADIFATUS SOLEHA",
    "stock": 0,
    "lastStock": 0,
    "lastUpdate": "2026-04-24T02:42:58Z",
    "cycle": 0
  },
  {
    "name": "SUROSO",
    "stock": 1,
    "lastStock": 0,
    "lastUpdate": "2026-04-23T18:04:20Z",
    "cycle": 0
  },
  {
    "name": "HADI SUTOYO",
    "stock": 0,
    "lastStock": 0,
    "lastUpdate": "2026-04-24T02:58:12Z",
    "cycle": 0
  },
  {
    "name": "SRI HIDAYATI",
    "stock": 0,
    "lastStock": 0,
    "lastUpdate": "2026-04-24T02:58:12Z",
    "cycle": 0
  },
  {
    "name": "ONG SWI GIOK",
    "stock": 0,
    "lastStock": 0,
    "lastUpdate": "2026-04-24T02:58:12Z",
    "cycle": 0
  },
  {
    "name": "YUSUF ISMAIL",
    "stock": 31,
    "lastStock": 0,
    "lastUpdate": "2026-04-23T18:06:40Z",
    "cycle": 0
  },
  {
    "name": "SUPARNI",
    "stock": 0,
    "lastStock": 54,
    "lastUpdate": "2026-04-24T02:58:53Z",
    "cycle": 0
  },
  {
    "name": "YOGA RAJAN",
    "stock": 0,
    "lastStock": 70,
    "lastUpdate": "2026-04-24T03:01:53Z",
    "cycle": 0
  },
  {
    "name": "ARIF FAUZI",
    "stock": 0,
    "lastStock": 0,
    "lastUpdate": "2026-04-24T03:01:53Z",
    "cycle": 0
  },
  {
    "name": "MOH HAFIF",
    "stock": 0,
    "lastStock": 0,
    "lastUpdate": "2026-04-24T03:01:53Z",
    "cycle": 0
  },
  {
    "name": "SAMSUL ARIFIN",
    "stock": 22,
    "lastStock": 0,
    "lastUpdate": "2026-04-24T00:05:00Z",
    "cycle": 0
  },
  {
    "name": "HERDIANA DIYAH S",
    "stock": 0,
    "lastStock": 0,
    "lastUpdate": "2026-04-24T03:02:32Z",
    "cycle": 0
  },
  {
    "name": "BUDI",
    "stock": 1,
    "lastStock": 0,
    "lastUpdate": "2026-04-23T18:10:08Z",
    "cycle": 0
  },
  {
    "name": "YULI SORAYA",
    "stock": 25,
    "lastStock": 0,
    "lastUpdate": "2026-04-24T00:13:52Z",
    "cycle": 0
  },
  {
    "name": "SUSILO",
    "stock": 0,
    "lastStock": 0,
    "lastUpdate": "2026-04-24T03:05:44Z",
    "cycle": 0
  },
  {
    "name": "HJ. HAERONI",
    "stock": 0,
    "lastStock": 0,
    "lastUpdate": "2026-04-24T03:10:42Z",
    "cycle": 0
  },
  {
    "name": "IMA",
    "stock": 0,
    "lastStock": 0,
    "lastUpdate": "2026-04-24T03:10:42Z",
    "cycle": 0
  },
  {
    "name": "DARMAWAN P",
    "stock": 0,
    "lastStock": 0,
    "lastUpdate": "2026-04-24T03:10:42Z",
    "cycle": 0
  },
  {
    "name": "DIYAH UTAMI",
    "stock": 0,
    "lastStock": 0,
    "lastUpdate": "2026-04-24T03:11:22Z",
    "cycle": 0
  },
  {
    "name": "TOKO ANITA",
    "stock": 0,
    "lastStock": 45,
    "lastUpdate": "2026-04-24T03:15:02Z",
    "cycle": 0
  },
  {
    "name": "TK. LUCKY",
    "stock": 0,
    "lastStock": 55,
    "lastUpdate": "2026-04-24T03:15:02Z",
    "cycle": 0
  },
  {
    "name": "UD SAMAN HADI",
    "stock": 0,
    "lastStock": 0,
    "lastUpdate": "2026-04-24T03:15:02Z",
    "cycle": 0
  },
  {
    "name": "SOEKAMTO",
    "stock": 0,
    "lastStock": 0,
    "lastUpdate": "2026-04-24T03:19:19Z",
    "cycle": 0
  },
  {
    "name": "TOKO TIARA",
    "stock": 0,
    "lastStock": 14,
    "lastUpdate": "2026-04-24T03:19:19Z",
    "cycle": 0
  },
  {
    "name": "TOKO POJOK",
    "stock": 127,
    "lastStock": 54,
    "lastUpdate": "2026-04-23T18:29:06Z",
    "cycle": 0
  },
  {
    "name": "UD RAHMAT",
    "stock": 54,
    "lastStock": 0,
    "lastUpdate": "2026-04-24T00:26:34Z",
    "cycle": 0
  },
  {
    "name": "ULFA MARIA",
    "stock": 0,
    "lastStock": 0,
    "lastUpdate": "2026-04-24T03:22:34Z",
    "cycle": 0
  },
  {
    "name": "TOKO SURYATI",
    "stock": 27,
    "lastStock": 1,
    "lastUpdate": "2026-04-23T18:37:39Z",
    "cycle": 0
  },
  {
    "name": "SUDJIONO",
    "stock": 0,
    "lastStock": 7,
    "lastUpdate": "2026-04-24T03:26:21Z",
    "cycle": 0
  },
  {
    "name": "ANDRI HERU CAHYONO",
    "stock": 0,
    "lastStock": 0,
    "lastUpdate": "2026-04-24T03:26:21Z",
    "cycle": 0
  },
  {
    "name": "ABDUL WAFI",
    "stock": 97,
    "lastStock": 0,
    "lastUpdate": "2026-04-23T18:44:06Z",
    "cycle": 0
  },
  {
    "name": "YUNIS WAHYUNI",
    "stock": 0,
    "lastStock": 0,
    "lastUpdate": "2026-04-24T03:33:41Z",
    "cycle": 0
  },
  {
    "name": "ROSIDI",
    "stock": 0,
    "lastStock": 0,
    "lastUpdate": "2026-04-24T03:33:41Z",
    "cycle": 0
  },
  {
    "name": "HJ. ASLAMIYAH",
    "stock": 0,
    "lastStock": 0,
    "lastUpdate": "2026-04-24T03:33:41Z",
    "cycle": 0
  },
  {
    "name": "TK. MAJU",
    "stock": 129,
    "lastStock": 0,
    "lastUpdate": "2026-04-23T18:52:53Z",
    "cycle": 0
  },
  {
    "name": "H. JUMAT",
    "stock": 0,
    "lastStock": 0,
    "lastUpdate": "2026-04-24T03:34:23Z",
    "cycle": 0
  },
  {
    "name": "HARSININGSIH",
    "stock": 25,
    "lastStock": 0,
    "lastUpdate": "2026-04-24T00:41:20Z",
    "cycle": 0
  },
  {
    "name": "CAHYA HERAWATI",
    "stock": 0,
    "lastStock": 2,
    "lastUpdate": "2026-04-24T03:36:55Z",
    "cycle": 0
  },
  {
    "name": "MISRI CICI",
    "stock": 0,
    "lastStock": 0,
    "lastUpdate": "2026-04-24T04:06:23Z",
    "cycle": 0
  },
  {
    "name": "ALFIAN DWI A.",
    "stock": 124,
    "lastStock": 63,
    "lastUpdate": "2026-04-23T18:59:37Z",
    "cycle": 0
  },
  {
    "name": "TOKO IRAWAN",
    "stock": 0,
    "lastStock": 0,
    "lastUpdate": "2026-04-24T04:06:23Z",
    "cycle": 0
  },
  {
    "name": "SUPARMAN",
    "stock": 33,
    "lastStock": 0,
    "lastUpdate": "2026-04-24T00:41:20Z",
    "cycle": 0
  },
  {
    "name": "P. SUK",
    "stock": 0,
    "lastStock": 0,
    "lastUpdate": "2026-04-24T03:47:43Z",
    "cycle": 0
  },
  {
    "name": "WIKAN K",
    "stock": 0,
    "lastStock": 0,
    "lastUpdate": "2026-04-24T03:47:43Z",
    "cycle": 0
  },
  {
    "name": "TITIK ISMIATIN",
    "stock": 88,
    "lastStock": 3,
    "lastUpdate": "2026-04-23T19:05:45Z",
    "cycle": 0
  },
  {
    "name": "SRI UTAMI",
    "stock": 0,
    "lastStock": 0,
    "lastUpdate": "2026-04-24T03:47:43Z",
    "cycle": 0
  },
  {
    "name": "TUSOK",
    "stock": 0,
    "lastStock": 0,
    "lastUpdate": "2026-04-24T03:54:46Z",
    "cycle": 0
  },
  {
    "name": "DJAMIAH",
    "stock": 1,
    "lastStock": 0,
    "lastUpdate": "2026-04-23T19:09:17Z",
    "cycle": 0
  },
  {
    "name": "SUMBER REJEKI",
    "stock": 117,
    "lastStock": 1,
    "lastUpdate": "2026-04-23T19:13:48Z",
    "cycle": 0
  },
  {
    "name": "ISTIQOMAH",
    "stock": 0,
    "lastStock": 0,
    "lastUpdate": "2026-04-24T03:54:46Z",
    "cycle": 0
  },
  {
    "name": "SALMAH",
    "stock": 10,
    "lastStock": 0,
    "lastUpdate": "2026-04-23T19:19:16Z",
    "cycle": 0
  }
]