[
  {
    "name": "AKBAR RISQ",
    "stock": 46,
    "lastStock": 0,
    "lastUpdate": "2026-04-09T06:09:57Z",
    "cycle": 4
  },
  {
    "name": "ATHI HANDAYANI",
    "stock": 0,
    "lastStock": 0,
    "lastUpdate": "2026-04-09T05:42:09Z",
    "cycle": 1
  },
  {
    "name": "CINDRAWATI",
    "stock": 0,
    "lastStock": 0,
    "lastUpdate": "2026-04-09T06:04:18Z",
    "cycle": 1
  },
  {
    "name": "EDI SUGENG SARIPAN",
    "stock": 0,
    "lastStock": 0,
    "lastUpdate": "2026-04-09T06:04:18Z",
    "cycle": 3
  },
  {
    "name": "BINA MAKMUR",
    "stock": 1,
    "lastStock": 0,
    "lastUpdate": "2026-04-09T06:09:57Z",
    "cycle": 4
  },
  {
    "name": "HENDRA KURNIAWAN",
    "stock": 32,
    "lastStock": 27,
    "lastUpdate": "2026-04-09T06:09:57Z",
    "cycle": 4
  },
  {
    "name": "SUCIYONO",
    "stock": 19,
    "lastStock": 0,
    "lastUpdate": "2026-04-09T06:09:57Z",
    "cycle": 4
  },
  {
    "name": "JAENAL",
    "stock": 67,
    "lastStock": 13,
    "lastUpdate": "2026-04-09T06:13:06Z",
    "cycle": 3
  },
  {
    "name": "JOKO SUWARNO",
    "stock": 22,
    "lastStock": 0,
    "lastUpdate": "2026-04-09T06:13:13Z",
    "cycle": 3
  },
  {
    "name": "KARSONO",
    "stock": 43,
    "lastStock": 0,
    "lastUpdate": "2026-04-09T06:13:53Z",
    "cycle": 3
  },
  {
    "name": "LUTFI A.",
    "stock": 27,
    "lastStock": 0,
    "lastUpdate": "2026-04-09T06:15:29Z",
    "cycle": 2
  },
  {
    "name": "MOH SAID",
    "stock": 0,
    "lastStock": 0,
    "lastUpdate": "2026-04-09T04:53:01Z",
    "cycle": 0
  },
  {
    "name": "TOKO 2 PUTRI",
    "stock": 0,
    "lastStock": 0,
    "lastUpdate": "2026-04-09T04:42:40Z",
    "cycle": 0
  },
  {
    "name": "TOKO IIN",
    "stock": 40,
    "lastStock": 0,
    "lastUpdate": "2026-04-09T06:16:26Z",
    "cycle": 1
  },
  {
    "name": "HJ LILIK LAILIYAH",
    "stock": 0,
    "lastStock": 0,
    "lastUpdate": "2026-04-09T04:32:44Z",
    "cycle": 0
  },
  {
    "name": "ERNA PUJIATI",
    "stock": 0,
    "lastStock": 0,
    "lastUpdate": "2026-04-09T04:32:58Z",
    "cycle": 0
  },
  {
    "name": "JONI H",
    "stock": 0,
    "lastStock": 0,
    "lastUpdate": "2026-04-09T05:11:52Z",
    "cycle": 0
  },
  {
    "name": "ROSA V",
    "stock": 0,
    "lastStock": 0,
    "lastUpdate": "2026-04-09T04:33:21Z",
    "cycle": 0
  },
  {
    "name": "LUKMAN BS",
    "stock": 0,
    "lastStock": 0,
    "lastUpdate": "2026-04-09T04:45:52Z",
    "cycle": 0
  },
  {
    "name": "BISTON MANURUNG",
    "stock": 0,
    "lastStock": 0,
    "lastUpdate": "2026-04-09T04:46:06Z",
    "cycle": 0
  },
  {
    "name": "JAMILAH",
    "stock": 0,
    "lastStock": 25,
    "lastUpdate": "2026-04-09T05:29:54Z",
    "cycle": 0
  },
  {
    "name": "YUDA",
    "stock": 0,
    "lastStock": 0,
    "lastUpdate": "2026-04-09T04:33:38Z",
    "cycle": 0
  },
  {
    "name": "BAMBANG HARTONO",
    "stock": 0,
    "lastStock": 0,
    "lastUpdate": "2026-04-09T04:34:00Z",
    "cycle": 0
  },
  {
    "name": "NADIFATUS SOLEHA",
    "stock": 0,
    "lastStock": 0,
    "lastUpdate": "2026-04-09T04:38:16Z",
    "cycle": 0
  },
  {
    "name": "SUROSO",
    "stock": 0,
    "lastStock": 0,
    "lastUpdate": "2026-04-09T04:38:38Z",
    "cycle": 0
  },
  {
    "name": "HADI SUTOYO",
    "stock": 0,
    "lastStock": 0,
    "lastUpdate": "2026-04-09T04:46:41Z",
    "cycle": 0
  },
  {
    "name": "SRI HIDAYATI",
    "stock": 0,
    "lastStock": 0,
    "lastUpdate": "2026-04-09T04:46:54Z",
    "cycle": 0
  },
  {
    "name": "ONG SWI GIOK",
    "stock": 0,
    "lastStock": 0,
    "lastUpdate": "2026-04-09T04:46:59Z",
    "cycle": 0
  },
  {
    "name": "YUSUF ISMAIL",
    "stock": 0,
    "lastStock": 0,
    "lastUpdate": "2026-04-09T04:38:50Z",
    "cycle": 0
  },
  {
    "name": "SUPARNI",
    "stock": 0,
    "lastStock": 54,
    "lastUpdate": "2026-04-09T05:03:36Z",
    "cycle": 0
  },
  {
    "name": "YOGA RAJAN",
    "stock": 0,
    "lastStock": 70,
    "lastUpdate": "2026-04-09T02:58:29Z",
    "cycle": 0
  },
  {
    "name": "ARIF FAUZI",
    "stock": 0,
    "lastStock": 0,
    "lastUpdate": "2026-04-09T04:47:53Z",
    "cycle": 0
  },
  {
    "name": "MOH HAFIF",
    "stock": 0,
    "lastStock": 0,
    "lastUpdate": "2026-04-09T04:48:32Z",
    "cycle": 0
  },
  {
    "name": "SAMSUL ARIFIN",
    "stock": 0,
    "lastStock": 0,
    "lastUpdate": "2026-04-09T04:53:01Z",
    "cycle": 0
  },
  {
    "name": "HERDIANA DIYAH S",
    "stock": 0,
    "lastStock": 0,
    "lastUpdate": "2026-04-09T04:53:45Z",
    "cycle": 0
  },
  {
    "name": "BUDI",
    "stock": 0,
    "lastStock": 60,
    "lastUpdate": "2026-04-09T03:07:49Z",
    "cycle": 0
  },
  {
    "name": "YULI SORAYA",
    "stock": 0,
    "lastStock": 0,
    "lastUpdate": "2026-04-09T04:58:41Z",
    "cycle": 0
  },
  {
    "name": "SUSILO",
    "stock": 0,
    "lastStock": 0,
    "lastUpdate": "2026-04-09T05:03:36Z",
    "cycle": 0
  },
  {
    "name": "HJ. HAERONI",
    "stock": 0,
    "lastStock": 0,
    "lastUpdate": "2026-04-09T04:39:16Z",
    "cycle": 0
  },
  {
    "name": "IMA",
    "stock": 0,
    "lastStock": 0,
    "lastUpdate": "2026-04-09T05:03:36Z",
    "cycle": 0
  },
  {
    "name": "DARMAWAN P",
    "stock": 0,
    "lastStock": 0,
    "lastUpdate": "2026-04-09T05:07:49Z",
    "cycle": 0
  },
  {
    "name": "DIYAH UTAMI",
    "stock": 0,
    "lastStock": 0,
    "lastUpdate": "2026-04-09T05:38:45Z",
    "cycle": 0
  },
  {
    "name": "SALMAH",
    "stock": 0,
    "lastStock": 0,
    "lastUpdate": "2026-04-09T05:07:49Z",
    "cycle": 0
  },
  {
    "name": "TOKO ANITA",
    "stock": 0,
    "lastStock": 45,
    "lastUpdate": "2026-04-09T05:38:45Z",
    "cycle": 0
  },
  {
    "name": "TK. LUCKY",
    "stock": 0,
    "lastStock": 55,
    "lastUpdate": "2026-04-09T05:38:45Z",
    "cycle": 0
  },
  {
    "name": "UD SAMAN HADI",
    "stock": 0,
    "lastStock": 0,
    "lastUpdate": "2026-04-09T05:07:49Z",
    "cycle": 0
  },
  {
    "name": "SOEKAMTO",
    "stock": 0,
    "lastStock": 0,
    "lastUpdate": "2026-04-09T05:11:52Z",
    "cycle": 0
  },
  {
    "name": "TOKO TIARA",
    "stock": 0,
    "lastStock": 14,
    "lastUpdate": "2026-04-09T05:11:52Z",
    "cycle": 0
  },
  {
    "name": "TOKO POJOK",
    "stock": 81,
    "lastStock": 54,
    "lastUpdate": "2026-04-09T05:11:52Z",
    "cycle": 0
  },
  {
    "name": "UD RAHMAT",
    "stock": 0,
    "lastStock": 0,
    "lastUpdate": "2026-04-09T03:07:49Z",
    "cycle": 0
  },
  {
    "name": "ULFA MARIA",
    "stock": 0,
    "lastStock": 0,
    "lastUpdate": "2026-04-09T05:17:03Z",
    "cycle": 0
  },
  {
    "name": "TOKO SURYATI",
    "stock": 22,
    "lastStock": 1,
    "lastUpdate": "2026-04-09T05:17:03Z",
    "cycle": 0
  },
  {
    "name": "SUDJIONO",
    "stock": 0,
    "lastStock": 7,
    "lastUpdate": "2026-04-09T03:19:13Z",
    "cycle": 0
  },
  {
    "name": "ANDRI HERU CAHYONO",
    "stock": 0,
    "lastStock": 0,
    "lastUpdate": "2026-04-09T02:40:42Z",
    "cycle": 0
  },
  {
    "name": "ABDUL WAFI",
    "stock": 84,
    "lastStock": 0,
    "lastUpdate": "2026-04-09T05:17:03Z",
    "cycle": 0
  },
  {
    "name": "YUNIS WAHYUNI",
    "stock": 0,
    "lastStock": 0,
    "lastUpdate": "2026-04-09T02:41:24Z",
    "cycle": 0
  },
  {
    "name": "ROSIDI",
    "stock": 0,
    "lastStock": 0,
    "lastUpdate": "2026-04-09T05:21:00Z",
    "cycle": 0
  },
  {
    "name": "HJ. ASLAMIYAH",
    "stock": 0,
    "lastStock": 0,
    "lastUpdate": "2026-04-09T02:45:06Z",
    "cycle": 0
  },
  {
    "name": "TK. MAJU",
    "stock": 63,
    "lastStock": 0,
    "lastUpdate": "2026-04-09T05:17:03Z",
    "cycle": 0
  },
  {
    "name": "H. JUMAT",
    "stock": 0,
    "lastStock": 0,
    "lastUpdate": "2026-04-09T03:19:13Z",
    "cycle": 0
  },
  {
    "name": "HARSININGSIH",
    "stock": 0,
    "lastStock": 0,
    "lastUpdate": "2026-04-09T05:25:00Z",
    "cycle": 0
  },
  {
    "name": "CAHYA HERAWATI",
    "stock": 1,
    "lastStock": 0,
    "lastUpdate": "2026-04-09T05:34:03Z",
    "cycle": 0
  },
  {
    "name": "MISRI CICI",
    "stock": 0,
    "lastStock": 0,
    "lastUpdate": "2026-04-09T03:19:13Z",
    "cycle": 0
  },
  {
    "name": "ALFIAN DWI A.",
    "stock": 83,
    "lastStock": 63,
    "lastUpdate": "2026-04-09T05:34:03Z",
    "cycle": 0
  },
  {
    "name": "TOKO IRAWAN",
    "stock": 0,
    "lastStock": 0,
    "lastUpdate": "2026-04-09T03:24:42Z",
    "cycle": 0
  },
  {
    "name": "SUPARMAN",
    "stock": 0,
    "lastStock": 0,
    "lastUpdate": "2026-04-09T02:48:34Z",
    "cycle": 0
  },
  {
    "name": "P. SUK",
    "stock": 0,
    "lastStock": 0,
    "lastUpdate": "2026-04-09T02:48:37Z",
    "cycle": 0
  },
  {
    "name": "WIKAN K",
    "stock": 0,
    "lastStock": 0,
    "lastUpdate": "2026-04-09T02:49:14Z",
    "cycle": 0
  },
  {
    "name": "TITIK ISMIATIN",
    "stock": 54,
    "lastStock": 3,
    "lastUpdate": "2026-04-09T05:38:45Z",
    "cycle": 0
  },
  {
    "name": "SRI UTAMI",
    "stock": 0,
    "lastStock": 0,
    "lastUpdate": "2026-04-09T02:54:33Z",
    "cycle": 0
  },
  {
    "name": "TUSOK",
    "stock": 0,
    "lastStock": 0,
    "lastUpdate": "2026-04-09T03:02:46Z",
    "cycle": 0
  },
  {
    "name": "DJAMIAH",
    "stock": 1,
    "lastStock": 0,
    "lastUpdate": "2026-04-09T05:39:27Z",
    "cycle": 0
  },
  {
    "name": "SUMBER REJEKI",
    "stock": 1,
    "lastStock": 0,
    "lastUpdate": "2026-04-09T05:39:29Z",
    "cycle": 0
  },
  {
    "name": "ISTIQOMAH",
    "stock": 0,
    "lastStock": 0,
    "lastUpdate": "2026-04-09T03:14:53Z",
    "cycle": 0
  }
]