[
  {
    "name": "AKBAR RISQ",
    "stock": 76,
    "lastStock": 0,
    "lastUpdate": "2026-03-17T01:25:36Z",
    "cycle": 5
  },
  {
    "name": "ATHI HANDAYANI",
    "stock": 20,
    "lastStock": 0,
    "lastUpdate": "2026-03-17T01:52:05Z",
    "cycle": 5
  },
  {
    "name": "CINDRAWATI",
    "stock": 0,
    "lastStock": 0,
    "lastUpdate": "2026-03-17T01:11:07Z",
    "cycle": 2
  },
  {
    "name": "EDI SUGENG SARIPAN",
    "stock": 16,
    "lastStock": 0,
    "lastUpdate": "2026-03-17T01:52:05Z",
    "cycle": 5
  },
  {
    "name": "BINA MAKMUR",
    "stock": 94,
    "lastStock": 0,
    "lastUpdate": "2026-03-17T01:11:59Z",
    "cycle": 5
  },
  {
    "name": "HENDRA KURNIAWAN",
    "stock": 3,
    "lastStock": 0,
    "lastUpdate": "2026-03-16T06:20:10Z",
    "cycle": 5
  },
  {
    "name": "SUCIYONO",
    "stock": 65,
    "lastStock": 0,
    "lastUpdate": "2026-03-17T02:06:13Z",
    "cycle": 5
  },
  {
    "name": "JAENAL",
    "stock": 35,
    "lastStock": 0,
    "lastUpdate": "2026-03-16T06:20:10Z",
    "cycle": 5
  },
  {
    "name": "JOKO SUWARNO",
    "stock": 57,
    "lastStock": 0,
    "lastUpdate": "2026-03-17T01:39:48Z",
    "cycle": 5
  },
  {
    "name": "KARSONO",
    "stock": 10,
    "lastStock": 0,
    "lastUpdate": "2026-03-16T06:20:10Z",
    "cycle": 5
  },
  {
    "name": "LUTFI A.",
    "stock": 52,
    "lastStock": 0,
    "lastUpdate": "2026-03-17T02:06:13Z",
    "cycle": 5
  },
  {
    "name": "MOH SAID",
    "stock": 30,
    "lastStock": 0,
    "lastUpdate": "2026-03-17T01:57:32Z",
    "cycle": 5
  },
  {
    "name": "TOKO 2 PUTRI",
    "stock": 23,
    "lastStock": 0,
    "lastUpdate": "2026-03-17T02:16:57Z",
    "cycle": 5
  },
  {
    "name": "TOKO IIN",
    "stock": 60,
    "lastStock": 0,
    "lastUpdate": "2026-03-17T01:58:28Z",
    "cycle": 5
  },
  {
    "name": "HJ LILIK LAILIYAH",
    "stock": 0,
    "lastStock": 0,
    "lastUpdate": "2026-03-17T01:50:09Z",
    "cycle": 1
  },
  {
    "name": "ERNA PUJIATI",
    "stock": 0,
    "lastStock": 0,
    "lastUpdate": "2026-03-17T02:28:22Z",
    "cycle": 4
  },
  {
    "name": "JONI H",
    "stock": 0,
    "lastStock": 0,
    "lastUpdate": "2026-03-17T02:03:29Z",
    "cycle": 1
  },
  {
    "name": "ROSA V",
    "stock": 6,
    "lastStock": 0,
    "lastUpdate": "2026-03-17T02:28:22Z",
    "cycle": 3
  },
  {
    "name": "LUKMAN BS",
    "stock": 23,
    "lastStock": 0,
    "lastUpdate": "2026-03-17T02:28:22Z",
    "cycle": 3
  },
  {
    "name": "BISTON MANURUNG",
    "stock": 0,
    "lastStock": 0,
    "lastUpdate": "2026-03-17T02:12:14Z",
    "cycle": 1
  },
  {
    "name": "JAMILAH",
    "stock": 0,
    "lastStock": 0,
    "lastUpdate": "2026-03-17T02:12:20Z",
    "cycle": 1
  },
  {
    "name": "YUDA",
    "stock": 0,
    "lastStock": 0,
    "lastUpdate": "2026-03-17T02:12:44Z",
    "cycle": 1
  },
  {
    "name": "BAMBANG HARTONO",
    "stock": 28,
    "lastStock": 0,
    "lastUpdate": "2026-03-17T02:28:22Z",
    "cycle": 2
  },
  {
    "name": "NADIFATUS SOLEHA",
    "stock": 13,
    "lastStock": 0,
    "lastUpdate": "2026-03-17T02:33:07Z",
    "cycle": 3
  },
  {
    "name": "SUROSO",
    "stock": 0,
    "lastStock": 0,
    "lastUpdate": "2026-03-17T02:23:05Z",
    "cycle": 2
  },
  {
    "name": "HADI SUTOYO",
    "stock": 0,
    "lastStock": 0,
    "lastUpdate": "2026-03-17T02:23:19Z",
    "cycle": 1
  },
  {
    "name": "SRI HIDAYATI",
    "stock": 0,
    "lastStock": 0,
    "lastUpdate": "2026-03-17T02:23:37Z",
    "cycle": 1
  },
  {
    "name": "ONG SWI GIOK",
    "stock": 0,
    "lastStock": 0,
    "lastUpdate": "2026-03-17T02:33:50Z",
    "cycle": 1
  },
  {
    "name": "YUSUF ISMAIL",
    "stock": 0,
    "lastStock": 0,
    "lastUpdate": "2026-03-17T02:33:59Z",
    "cycle": 1
  },
  {
    "name": "SUPARNI",
    "stock": 0,
    "lastStock": 0,
    "lastUpdate": "2026-03-17T02:34:23Z",
    "cycle": 1
  },
  {
    "name": "YOGA RAJAN",
    "stock": 0,
    "lastStock": 0,
    "lastUpdate": "2026-03-17T02:34:46Z",
    "cycle": 1
  },
  {
    "name": "ARIF FAUZI",
    "stock": 0,
    "lastStock": 0,
    "lastUpdate": "2026-03-16T04:41:22Z",
    "cycle": 0
  },
  {
    "name": "MOH HAFIF",
    "stock": 0,
    "lastStock": 0,
    "lastUpdate": "2026-03-16T04:48:18Z",
    "cycle": 0
  },
  {
    "name": "SAMSUL ARIFIN",
    "stock": 0,
    "lastStock": 0,
    "lastUpdate": "2026-03-16T04:48:18Z",
    "cycle": 0
  },
  {
    "name": "HERDIANA DIYAH S",
    "stock": 0,
    "lastStock": 0,
    "lastUpdate": "2026-03-16T05:10:23Z",
    "cycle": 0
  },
  {
    "name": "BUDI",
    "stock": 0,
    "lastStock": 0,
    "lastUpdate": "2026-03-16T04:48:18Z",
    "cycle": 0
  },
  {
    "name": "YULI SORAYA",
    "stock": 1,
    "lastStock": 0,
    "lastUpdate": "2026-03-16T14:35:33Z",
    "cycle": 1
  },
  {
    "name": "SUSILO",
    "stock": 1,
    "lastStock": 0,
    "lastUpdate": "2026-03-16T14:35:33Z",
    "cycle": 1
  },
  {
    "name": "HJ. HAERONI",
    "stock": 1,
    "lastStock": 0,
    "lastUpdate": "2026-03-16T14:35:33Z",
    "cycle": 1
  },
  {
    "name": "IMA",
    "stock": 1,
    "lastStock": 0,
    "lastUpdate": "2026-03-16T14:35:40Z",
    "cycle": 1
  },
  {
    "name": "DARMAWAN P",
    "stock": 0,
    "lastStock": 0,
    "lastUpdate": "2026-03-16T04:51:19Z",
    "cycle": 0
  },
  {
    "name": "DIYAH UTAMI",
    "stock": 0,
    "lastStock": 0,
    "lastUpdate": "2026-03-16T05:10:23Z",
    "cycle": 0
  },
  {
    "name": "SALMAH",
    "stock": 0,
    "lastStock": 0,
    "lastUpdate": "2026-03-16T04:57:10Z",
    "cycle": 0
  },
  {
    "name": "TOKO ANITA",
    "stock": 0,
    "lastStock": 0,
    "lastUpdate": "2026-03-16T04:57:10Z",
    "cycle": 0
  },
  {
    "name": "TK. LUCKY",
    "stock": 0,
    "lastStock": 0,
    "lastUpdate": "2026-03-16T04:57:10Z",
    "cycle": 0
  },
  {
    "name": "UD SAMAN HADI",
    "stock": 0,
    "lastStock": 0,
    "lastUpdate": "2026-03-16T05:03:46Z",
    "cycle": 0
  },
  {
    "name": "SOEKAMTO",
    "stock": 0,
    "lastStock": 0,
    "lastUpdate": "2026-03-16T05:03:46Z",
    "cycle": 0
  },
  {
    "name": "TOKO TIARA",
    "stock": 0,
    "lastStock": 0,
    "lastUpdate": "2026-03-16T05:17:33Z",
    "cycle": 0
  },
  {
    "name": "TOKO POJOK",
    "stock": 46,
    "lastStock": 0,
    "lastUpdate": "2026-03-16T06:37:30Z",
    "cycle": 5
  },
  {
    "name": "UD RAHMAT",
    "stock": 0,
    "lastStock": 0,
    "lastUpdate": "2026-03-16T06:07:46Z",
    "cycle": 1
  },
  {
    "name": "ULFA MARIA",
    "stock": 0,
    "lastStock": 0,
    "lastUpdate": "2026-03-16T05:17:33Z",
    "cycle": 0
  },
  {
    "name": "TOKO SURYATI",
    "stock": 0,
    "lastStock": 0,
    "lastUpdate": "2026-03-16T04:51:48Z",
    "cycle": 0
  },
  {
    "name": "SUDJIONO",
    "stock": 0,
    "lastStock": 0,
    "lastUpdate": "2026-03-16T05:17:33Z",
    "cycle": 0
  },
  {
    "name": "ANDRI HERU CAHYONO",
    "stock": 0,
    "lastStock": 0,
    "lastUpdate": "2026-03-16T05:17:33Z",
    "cycle": 0
  },
  {
    "name": "ABDUL WAFI",
    "stock": 40,
    "lastStock": 0,
    "lastUpdate": "2026-03-16T06:37:30Z",
    "cycle": 5
  },
  {
    "name": "YUNIS WAHYUNI",
    "stock": 0,
    "lastStock": 0,
    "lastUpdate": "2026-03-16T05:36:24Z",
    "cycle": 0
  },
  {
    "name": "ROSIDI",
    "stock": 0,
    "lastStock": 0,
    "lastUpdate": "2026-03-16T05:24:55Z",
    "cycle": 0
  },
  {
    "name": "HJ. ASLAMIYAH",
    "stock": 0,
    "lastStock": 0,
    "lastUpdate": "2026-03-16T05:24:55Z",
    "cycle": 0
  },
  {
    "name": "TK. MAJU",
    "stock": 0,
    "lastStock": 0,
    "lastUpdate": "2026-03-16T05:03:46Z",
    "cycle": 0
  },
  {
    "name": "H. JUMAT",
    "stock": 0,
    "lastStock": 0,
    "lastUpdate": "2026-03-16T05:36:24Z",
    "cycle": 0
  },
  {
    "name": "HARSININGSIH",
    "stock": 0,
    "lastStock": 0,
    "lastUpdate": "2026-03-16T06:26:01Z",
    "cycle": 1
  },
  {
    "name": "CAHYA HERAWATI",
    "stock": 0,
    "lastStock": 0,
    "lastUpdate": "2026-03-16T06:26:06Z",
    "cycle": 1
  },
  {
    "name": "MISRI CICI",
    "stock": 0,
    "lastStock": 0,
    "lastUpdate": "2026-03-16T06:26:14Z",
    "cycle": 1
  },
  {
    "name": "ALFIAN DWI A.",
    "stock": 1,
    "lastStock": 0,
    "lastUpdate": "2026-03-16T06:47:21Z",
    "cycle": 5
  },
  {
    "name": "ISTIQOMAH",
    "stock": 0,
    "lastStock": 0,
    "lastUpdate": "2026-03-16T06:35:03Z",
    "cycle": 1
  },
  {
    "name": "TOKO IRAWAN",
    "stock": 0,
    "lastStock": 0,
    "lastUpdate": "2026-03-16T05:36:24Z",
    "cycle": 0
  },
  {
    "name": "SUMBER REJEKI",
    "stock": 0,
    "lastStock": 1,
    "lastUpdate": "2026-03-16T06:35:33Z",
    "cycle": 1
  },
  {
    "name": "SUPARMAN",
    "stock": 0,
    "lastStock": 0,
    "lastUpdate": "2026-03-16T06:36:03Z",
    "cycle": 1
  },
  {
    "name": "P. SUK",
    "stock": 0,
    "lastStock": 18,
    "lastUpdate": "2026-03-16T06:36:18Z",
    "cycle": 1
  },
  {
    "name": "WIKAN K",
    "stock": 0,
    "lastStock": 0,
    "lastUpdate": "2026-03-17T01:05:40Z",
    "cycle": 2
  },
  {
    "name": "TUSOK",
    "stock": 0,
    "lastStock": 0,
    "lastUpdate": "2026-03-17T01:05:47Z",
    "cycle": 2
  },
  {
    "name": "DJAMIAH",
    "stock": 1,
    "lastStock": 0,
    "lastUpdate": "2026-03-17T01:05:48Z",
    "cycle": 5
  },
  {
    "name": "TITIK ISMIATIN",
    "stock": 80,
    "lastStock": 3,
    "lastUpdate": "2026-03-17T01:05:50Z",
    "cycle": 1
  },
  {
    "name": "SRI UTAMI",
    "stock": 0,
    "lastStock": 0,
    "lastUpdate": "2026-03-17T01:06:17Z",
    "cycle": 1
  }
]